sfinance/__init__.py
sfinance/exceptions.py
sfinance/fetcher.py
sfinance/sfinance.py
sfinance/stock_screener.py
sfinance/ticker.py
sfinance-0.1.4.dist-info/licenses/AUTHORS.rst
sfinance-0.1.4.dist-info/licenses/LICENSE
sfinance-0.1.4.dist-info/METADATA
sfinance-0.1.4.dist-info/WHEEL
sfinance-0.1.4.dist-info/top_level.txt
sfinance-0.1.4.dist-info/RECORD
