Metadata-Version: 2.4
Name: sfinance
Version: 0.1.4
Summary: it is a lightweight Python library for extracting financial data from structured, publicly accessible stock information pages
Author-email: shiva kharbanda <shivakharbanda1311@gmail.com>
Maintainer-email: shiva kharbanda <shivakharbanda1311@gmail.com>
License: Apache Software License 2.0
Project-URL: bugs, https://github.com/shivakharbanda/sfinance/issues
Project-URL: changelog, https://github.com/shivakharbanda/sfinance/blob/master/changelog.md
Project-URL: homepage, https://github.com/shivakharbanda/sfinance
License-File: LICENSE
License-File: AUTHORS.rst
Requires-Dist: selenium>=4.33.0
Requires-Dist: beautifulsoup4>=4.13.4
Requires-Dist: pandas>=2.0.0
Requires-Dist: html5lib
Provides-Extra: dev
Requires-Dist: coverage; extra == "dev"
Requires-Dist: mypy; extra == "dev"
Requires-Dist: pytest; extra == "dev"
Requires-Dist: ruff; extra == "dev"
Dynamic: license-file
